bayse_tools/common_utilities/__init__.py
bayse_tools/common_utilities/bayseflow.py
bayse_tools/common_utilities/captureutils.py
bayse_tools/common_utilities/dnsutils.py
bayse_tools/common_utilities/iputils.py
bayse_tools/common_utilities/packet.py
bayse_tools/common_utilities/utilities.py
bayse_tools/converter/__init__.py
bayse_tools/converter/convert.py
bayse_tools/converter/generic_flowutils.py
bayse_tools/converter/interflow.py
bayse_tools/converter/interflowutils.py
bayse_tools/converter/ipfix.py
bayse_tools/converter/ipfixutils.py
bayse_tools/converter/netflow_v9.py
bayse_tools/converter/netflowutils.py
bayse_tools/converter/pcaputils.py
bayse_tools/converter/tests.py
bayse_tools/converter/zeekflow.py
bayse_tools/converter/zeekutils.py
bayse_tools/converter/tests/expectedOutputs/testCase10_oneNonLocalFlowIsProcessable.conn.bf
bayse_tools/converter/tests/expectedOutputs/testCase11_emptySansHeaders.conn.bf
bayse_tools/converter/tests/expectedOutputs/testCase12_icmp_plus_others.conn.bf
bayse_tools/converter/tests/expectedOutputs/testCase13_mtbDotcom_bangInPlaceOfDot_filtered.bf
bayse_tools/converter/tests/expectedOutputs/testCase14_faturasatacada_phish_with_nonephemeral_dport9999_filtered.bf
bayse_tools/converter/tests/expectedOutputs/testCase15_chromeWin10StartChromeBrowser_JSON.conn.bf
bayse_tools/converter/tests/expectedOutputs/testCase16_chromeWin10VisitAmazonScamaDotCom_JSON.conn.bf
bayse_tools/converter/tests/expectedOutputs/testCase17_oneLocalFlowIsProcessable_JSON.conn.bf
bayse_tools/converter/tests/expectedOutputs/testCase18_oneNonLocalFlowIsProcessable_JSON.conn.bf
bayse_tools/converter/tests/expectedOutputs/testCase19_icmp_plus_others_JSON.conn.bf
bayse_tools/converter/tests/expectedOutputs/testCase1_chromeWin10StartChromeBrowser_filtered.bf
bayse_tools/converter/tests/expectedOutputs/testCase20_oneNonLocalFlowIsProcessable_newstyle_JSON.conn.bf
bayse_tools/converter/tests/expectedOutputs/testCase21_icmp_plus_others_newstyle_JSON.conn.bf
bayse_tools-1.0.5.dist-info/LICENSE
bayse_tools-1.0.5.dist-info/METADATA
bayse_tools-1.0.5.dist-info/WHEEL
bayse_tools-1.0.5.dist-info/top_level.txt
bayse_tools-1.0.5.dist-info/RECORD
